modsman/__init__.py
modsman/api.py
modsman/cli.py
modsman/common.py
modsman/modlist.py
modsman/modsman.py
modsman/murmur2.py
modsman-0.6.0.dist-info/entry_points.txt
modsman-0.6.0.dist-info/WHEEL
modsman-0.6.0.dist-info/METADATA
modsman-0.6.0.dist-info/RECORD
