Metadata-Version: 2.1
Name: modsman
Version: 0.6.0
Summary: A Minecraft mod manager for the command line.
Home-page: https://gitlab.com/sargunv-mc-mods/modsman
License: Apache-2.0
Author: Sargun Vohra
Author-email: sargun.vohra@gmail.com
Requires-Python: >=3.7,<4.0
Classifier: License :: OSI Approved :: Apache Software License
Classifier: Programming Language :: Python :: 3
Classifier: Programming Language :: Python :: 3.7
Requires-Dist: aiofiles (>=0.4.0,<0.5.0)
Requires-Dist: aiohttp (>=3.5,<4.0)
Requires-Dist: pathlib (>=1.0,<2.0)
Project-URL: Repository, https://gitlab.com/sargunv-mc-mods/modsman
